qdill/__init__.py
qdill-1.1.dist-info/LICENSE
qdill-1.1.dist-info/METADATA
qdill-1.1.dist-info/WHEEL
qdill-1.1.dist-info/top_level.txt
qdill-1.1.dist-info/RECORD
