Metadata-Version: 2.1
Name: qdill
Version: 1.1
Summary: tiny convenience lib for dill
Home-page: https://github.com/madgen-content/qdill
Author: madgen
Author-email: madgencontent@gmail.com
License: UNKNOWN
Platform: UNKNOWN
Requires-Dist: dill
